tests/__init__.py
tests/test_ypclient.py
tests/testapi/__init__.py
tests/testapi/test_flow.py
tests/testapi/test_sign.py
tests/testapi/test_sms.py
tests/testapi/test_tpl.py
tests/testapi/test_user.py
tests/testapi/test_voice.py
yunpian_python_sdk/__init__.py
yunpian_python_sdk/ypclient.py
yunpian_python_sdk/api/__init__.py
yunpian_python_sdk/api/flow.py
yunpian_python_sdk/api/sign.py
yunpian_python_sdk/api/sms.py
yunpian_python_sdk/api/tpl.py
yunpian_python_sdk/api/user.py
yunpian_python_sdk/api/voice.py
yunpian_python_sdk/api/ypapi.py
yunpian_python_sdk/model/__init__.py
yunpian_python_sdk/model/constant.py
yunpian_python_sdk/model/result.py
yunpian_python_sdk-1.0.0.dist-info/DESCRIPTION.rst
yunpian_python_sdk-1.0.0.dist-info/METADATA
yunpian_python_sdk-1.0.0.dist-info/RECORD
yunpian_python_sdk-1.0.0.dist-info/WHEEL
yunpian_python_sdk-1.0.0.dist-info/metadata.json
yunpian_python_sdk-1.0.0.dist-info/top_level.txt
