Metadata-Version: 1.2
Name: yunpian-python-sdk
Version: 1.0.0
Summary: Yunpian Python SDK
Home-page: https://github.com/yunpian/yunpian-python-sdk
Author: dzh
Author-email: daizhong@yunpian.com
License: MIT
Download-URL: https://pypi.python.org/pypi/yunpian-python-sdk
Keywords: yunpian sdk
Platform: UNKNOWN
Classifier: Development Status :: 5 - Production/Stable
Classifier: Intended Audience :: Developers
Classifier: License :: OSI Approved :: MIT License
Classifier: Natural Language :: Chinese (Simplified)
Classifier: Operating System :: OS Independent
Classifier: Programming Language :: Python :: 2
Classifier: Programming Language :: Python :: 2.7
Classifier: Programming Language :: Python :: 3
Classifier: Programming Language :: Python :: 3.4
Classifier: Programming Language :: Python :: 3.5
Classifier: Programming Language :: Python :: 3.6
Classifier: Topic :: Software Development :: Libraries :: Python Modules
Requires-Python: >=2.7, !=3.0.*, !=3.1.*, !=3.2.*, !=3.3.*, <4
